setup.py
calo_calculator/Calo.py
calo_calculator/Calo_test.py
calo_calculator/__init__.py
calo_calculator.egg-info/PKG-INFO
calo_calculator.egg-info/SOURCES.txt
calo_calculator.egg-info/dependency_links.txt
calo_calculator.egg-info/not-zip-safe
calo_calculator.egg-info/top_level.txt