Metadata-Version: 1.0
Name: calo-calculator
Version: 1.0
Summary: calo_calculator
Home-page: UNKNOWN
Author: UNKNOWN
Author-email: UNKNOWN
License: UNKNOWN
Platform: UNKNOWN
